setup.py
distributions_by_gaurav/Binomialdistribution.py
distributions_by_gaurav/Gaussiandistribution.py
distributions_by_gaurav/Generaldistribution.py
distributions_by_gaurav/__init__.py
distributions_by_gaurav.egg-info/PKG-INFO
distributions_by_gaurav.egg-info/SOURCES.txt
distributions_by_gaurav.egg-info/dependency_links.txt
distributions_by_gaurav.egg-info/not-zip-safe
distributions_by_gaurav.egg-info/top_level.txt