Metadata-Version: 1.0
Name: distributions-by-gaurav
Version: 0.11
Summary: Gaussian distributions, Binomial distributions
Home-page: UNKNOWN
Author: UNKNOWN
Author-email: UNKNOWN
License: UNKNOWN
Platform: UNKNOWN
